{
  "amobbs": {
    "login_methods": [
      "qrcode",
      "password",
      "cookie"
    ],
    "detail": "FULL",
    "error": null
  },
  "bilibili": {
    "login_methods": [
      "qrcode",
      "password",
      "oauth",
      "cookie"
    ],
    "detail": "FULL",
    "error": null
  },
  "csdn": {
    "login_methods": [
      "qrcode",
      "password",
      "oauth",
      "cookie"
    ],
    "detail": "FULL",
    "error": null
  },
  "dewu": {
    "login_methods": [
      "password",
      "phone",
      "qrcode",
      "oauth",
      "cookie"
    ],
    "detail": "FULL",
    "error": null
  },
  "discuz": {
    "login_methods": [
      "qrcode",
      "password",
      "cookie"
    ],
    "detail": "FULL",
    "error": null
  },
  "douban": {
    "login_methods": [
      "qrcode",
      "phone",
      "cookie"
    ],
    "detail": "FULL",
    "error": null
  },
  "juejin": {
    "login_methods": [
      "qrcode",
      "phone",
      "oauth",
      "cookie"
    ],
    "detail": "FULL",
    "error": null
  },
  "mydigit": {
    "login_methods": [
      "qrcode",
      "password",
      "cookie"
    ],
    "detail": "FULL",
    "error": null
  },
  "oshwhub": {
    "login_methods": [
      "qrcode",
      "oauth",
      "cookie"
    ],
    "detail": "FULL",
    "error": null
  },
  "rss": {
    "login_methods": [],
    "detail": "BASIC",
    "error": null
  },
  "smzdm": {
    "login_methods": [
      "password",
      "phone",
      "oauth",
      "cookie"
    ],
    "detail": "FULL",
    "error": null
  },
  "twitter": {
    "login_methods": [
      "oauth1",
      "bearer"
    ],
    "detail": "FULL",
    "error": null
  },
  "wechat_mp": {
    "login_methods": [
      "qrcode",
      "password",
      "oauth",
      "cookie"
    ],
    "detail": "FULL",
    "error": null
  },
  "wordpress": {
    "login_methods": [
      "password",
      "cookie"
    ],
    "detail": "FULL",
    "error": null
  },
  "xianyu_auto_reply": {
    "login_methods": [
      "cookie"
    ],
    "detail": "BASIC",
    "error": null
  },
  "xianyu": {
    "login_methods": [
      "qrcode",
      "oauth",
      "cookie"
    ],
    "detail": "FULL",
    "error": null
  },
  "xianyu_products": {
    "login_methods": [
      "password",
      "qrcode",
      "cookie"
    ],
    "detail": "FULL",
    "error": null
  },
  "xiaohongshu": {
    "login_methods": [
      "phone",
      "qrcode",
      "oauth",
      "cookie"
    ],
    "detail": "FULL",
    "error": null
  },
  "zhihu": {
    "login_methods": [
      "qrcode",
      "phone",
      "cookie"
    ],
    "detail": "FULL",
    "error": null
  },
  "_last_checked_at": "2026-07-08T01:11:54"
}